gym_discrete/__init__.py
gym_discrete/envs/__init__.py
gym_discrete/envs/discrete_env.py
gym_discrete-1.5.6.dist-info/LICENSE
gym_discrete-1.5.6.dist-info/METADATA
gym_discrete-1.5.6.dist-info/WHEEL
gym_discrete-1.5.6.dist-info/top_level.txt
gym_discrete-1.5.6.dist-info/RECORD
