Metadata-Version: 2.1
Name: gym-discrete
Version: 1.5.6
Summary: A OpenAI Gym Env for discrete
Home-page: UNKNOWN
Author: Claudia Viaro
License: MIT
Platform: UNKNOWN
Requires-Dist: gym
